pyschare/__init__.py
pyschare/constants.py
pyschare/data_functions.py
pyschare/explore/__init__.py
pyschare/explore/explore.py
pyschare/search/__init__.py
pyschare/search/data/__init__.py
pyschare/search/data/access_data.py
pyschare/search/data/adjusted_graduation_rate_2010.csv
pyschare/search/data/adjusted_graduation_rate_2011.csv
pyschare/search/data/adjusted_graduation_rate_2012.csv
pyschare/search/data/adjusted_graduation_rate_2013.csv
pyschare/search/data/adjusted_graduation_rate_2014.csv
pyschare/search/data/adjusted_graduation_rate_2015.csv
pyschare/search/data/adjusted_graduation_rate_2016.csv
pyschare/search/data/adjusted_graduation_rate_2017.csv
pyschare/search/data/adjusted_graduation_rate_2018.csv
pyschare/search/data/ahs_national_household_2015.csv
pyschare/search/data/ahs_national_household_2017.csv
pyschare/search/data/ahs_national_household_2019.csv
pyschare/search/data/ahs_national_household_2021.csv
pyschare/search/data/ahs_national_household_2023.csv
pyschare/search/data/ahs_national_mortage_2015.csv
pyschare/search/data/ahs_national_mortage_2017.csv
pyschare/search/data/ahs_national_mortage_2019.csv
pyschare/search/data/ahs_national_mortage_2021.csv
pyschare/search/data/ahs_national_mortgage_2023.csv
pyschare/search/data/ahs_national_person_2015.csv
pyschare/search/data/ahs_national_person_2017.csv
pyschare/search/data/ahs_national_person_2019.csv
pyschare/search/data/ahs_national_person_2021.csv
pyschare/search/data/ahs_national_person_2023.csv
pyschare/search/data/ahs_national_project_2015.csv
pyschare/search/data/ahs_national_project_2017.csv
pyschare/search/data/ahs_national_project_2019.csv
pyschare/search/data/ahs_national_project_2021.csv
pyschare/search/data/ahs_national_project_2023.csv
pyschare/search/data/american_community_survey_2010.csv
pyschare/search/data/american_community_survey_2011.csv
pyschare/search/data/american_community_survey_2012.csv
pyschare/search/data/american_community_survey_2013.csv
pyschare-0.0.9.0.0.dist-info/METADATA
pyschare-0.0.9.0.0.dist-info/WHEEL
pyschare-0.0.9.0.0.dist-info/RECORD
