Metadata-Version: 2.3
Name: PySCHARE
Version: 0.0.9.0.0
Summary: PySCHARE Python package
License: MIT
Author: Elif Dede Yildirim
Author-email: dedeyildirime2@nih.gov
Requires-Python: >=3.10
Classifier: License :: OSI Approved :: MIT License
Classifier: Programming Language :: Python :: 3
Classifier: Programming Language :: Python :: 3.10
Classifier: Programming Language :: Python :: 3.11
Classifier: Programming Language :: Python :: 3.12
Classifier: Programming Language :: Python :: 3.13
Requires-Dist: IPython (>=7.22,<8.0)
Requires-Dist: ipywidgets (>=7.6,<8.0)
Requires-Dist: matplotlib (>=3.4.2,<4.0.0)
Requires-Dist: numpy (>=1.21,<2.0)
Requires-Dist: pandas (>=1.3.1,<2.0.0)
Requires-Dist: seaborn (>=0.11.1,<0.12.0)
